texttube/__init__.py
texttube-0.1.0.dist-info/WHEEL
texttube-0.1.0.dist-info/METADATA
texttube-0.1.0.dist-info/RECORD
